multiscale_phate/__init__.py
multiscale_phate/compress.py
multiscale_phate/condense.py
multiscale_phate/diffuse.py
multiscale_phate/embed.py
multiscale_phate/multiscale_phate.py
multiscale_phate/tree.py
multiscale_phate/utils.py
multiscale_phate/version.py
multiscale_phate/visualize.py
multiscale_phate-0.0.dist-info/LICENSE
multiscale_phate-0.0.dist-info/METADATA
multiscale_phate-0.0.dist-info/WHEEL
multiscale_phate-0.0.dist-info/top_level.txt
multiscale_phate-0.0.dist-info/RECORD
