Metadata-Version: 2.1
Name: multiscale-phate
Version: 0.0
Summary: multiscale_phate
Home-page: https://github.com/KrishnaswamyLab/Multiscale_PHATE
Author: Manik Kuchroo & Scott Gigante, Yale University
Author-email: manik.kuchroo@yale.edu
License: GNU General Public License Version 3
Download-URL: https://github.com/KrishnaswamyLab/Multiscale_PHATE/archive/v0.0.tar.gz
Keywords: big-data,computational-biology,dimensionality-reduction,visualization,embedding,manifold-learning
Platform: UNKNOWN
Classifier: Development Status :: 3 - Alpha
Classifier: Environment :: Console
Classifier: Framework :: Jupyter
Classifier: Intended Audience :: Developers
Classifier: Intended Audience :: Science/Research
Classifier: Natural Language :: English
Classifier: Operating System :: MacOS :: MacOS X
Classifier: Operating System :: Microsoft :: Windows
Classifier: Operating System :: POSIX :: Linux
Classifier: Programming Language :: Python :: 3
Classifier: Programming Language :: Python :: 3.5
Classifier: Programming Language :: Python :: 3.6
Classifier: Programming Language :: Python :: 3.7
Classifier: Topic :: Scientific/Engineering :: Bio-Informatics
Classifier: Topic :: Scientific/Engineering :: Visualization
Requires-Python: >=3.6
Requires-Dist: numpy
Requires-Dist: scipy
Requires-Dist: graphtools
Requires-Dist: phate
Requires-Dist: scikit-learn
Requires-Dist: tasklogger
Requires-Dist: joblib
Provides-Extra: test
Requires-Dist: nose2 ; extra == 'test'
Requires-Dist: numpy ; extra == 'test'
Requires-Dist: coverage ; extra == 'test'
Requires-Dist: coveralls ; extra == 'test'
Requires-Dist: parameterized ; extra == 'test'
Requires-Dist: black ; extra == 'test'
